gatecoin_contracts/CHANGELOG.md
gatecoin_contracts/__init__.py
gatecoin_contracts/constants.py
gatecoin_contracts/contract_manager.py
gatecoin_contracts/contract_source_manager.py
gatecoin_contracts/py.typed
gatecoin_contracts/data/contracts.json
gatecoin_contracts/data/deployment_arbitrum-one.json
gatecoin_contracts/data/deployment_goerli.json
gatecoin_contracts/data/deployment_goerli_unstable.json
gatecoin_contracts/data/deployment_rinkeby-arbitrum.json
gatecoin_contracts/data/deployment_services_arbitrum-one.json
gatecoin_contracts/data/deployment_services_goerli.json
gatecoin_contracts/data/deployment_services_goerli_unstable.json
gatecoin_contracts/data/deployment_services_rinkeby-arbitrum.json
gatecoin_contracts/data/gas.json
gatecoin_contracts/data/source/__init__.py
gatecoin_contracts/data/source/gatecoin/Controllable.sol
gatecoin_contracts/data/source/gatecoin/SecretRegistry.sol
gatecoin_contracts/data/source/gatecoin/Token.sol
gatecoin_contracts/data/source/gatecoin/TokenNetwork.sol
gatecoin_contracts/data/source/gatecoin/TokenNetworkRegistry.sol
gatecoin_contracts/data/source/gatecoin/Utils.sol
gatecoin_contracts/data/source/lib/ECVerify.sol
gatecoin_contracts/data/source/lib/MessageType.sol
gatecoin_contracts/data/source/services/MonitoringService.sol
gatecoin_contracts/data/source/services/OneToN.sol
gatecoin_contracts/data/source/services/ServiceRegistry.sol
gatecoin_contracts/data/source/services/UserDeposit.sol
gatecoin_contracts/data/source/test/CustomToken.sol
gatecoin_contracts/data/source/test/HumanStandardToken.sol
gatecoin_contracts/data/source/test/MonitoringServiceInternalsTest.sol
gatecoin_contracts/data/source/test/OneToNInternalsTest.sol
gatecoin_contracts/data/source/test/SignatureVerifyTest.sol
gatecoin_contracts/data/source/test/StandardToken.sol
gatecoin_contracts/data/source/test/TokenNetworkInternalsTest.sol
gatecoin_contracts/data/source/test/UDCTransfer.sol
gatecoin_contracts/data/source/test/__init__.py
gatecoin_contracts-0.1.0.dist-info/licenses/LICENSE
gatecoin_contracts-0.1.0.dist-info/METADATA
gatecoin_contracts-0.1.0.dist-info/WHEEL
gatecoin_contracts-0.1.0.dist-info/entry_points.txt
gatecoin_contracts-0.1.0.dist-info/top_level.txt
gatecoin_contracts-0.1.0.dist-info/RECORD
