Metadata-Version: 2.4
Name: gatecoin-contracts
Version: 0.1.0
Summary: Gatecoin contracts library and utilities
Author-email: Md Sulaiman <dev.sulaiman@icloud.com>
License: MIT
Keywords: gatecoin,ethereum,blockchain
Requires-Python: >=3.8
License-File: LICENSE
Dynamic: license-file
